odoo9_addon_medical_patient_dob-9.0.1.0.0.99.dev8-py2.7-nspkg.pth
odoo9_addon_medical_patient_dob-9.0.1.0.0.99.dev8.dist-info/DESCRIPTION.rst
odoo9_addon_medical_patient_dob-9.0.1.0.0.99.dev8.dist-info/METADATA
odoo9_addon_medical_patient_dob-9.0.1.0.0.99.dev8.dist-info/RECORD
odoo9_addon_medical_patient_dob-9.0.1.0.0.99.dev8.dist-info/WHEEL
odoo9_addon_medical_patient_dob-9.0.1.0.0.99.dev8.dist-info/metadata.json
odoo9_addon_medical_patient_dob-9.0.1.0.0.99.dev8.dist-info/namespace_packages.txt
odoo9_addon_medical_patient_dob-9.0.1.0.0.99.dev8.dist-info/top_level.txt
odoo_addons/medical_patient_dob/README.rst
odoo_addons/medical_patient_dob/__init__.py
odoo_addons/medical_patient_dob/__openerp__.py
odoo_addons/medical_patient_dob/i18n/es_CO.po
odoo_addons/medical_patient_dob/i18n/pt_BR.po
odoo_addons/medical_patient_dob/models/__init__.py
odoo_addons/medical_patient_dob/models/medical_patient.py
odoo_addons/medical_patient_dob/static/description/icon.png
odoo_addons/medical_patient_dob/tests/__init__.py
odoo_addons/medical_patient_dob/tests/test_medical_patient.py
